speechtoolkit/__init__.py
speechtoolkit/asr/__init__.py
speechtoolkit/asr/distilwhisper_lib.py
speechtoolkit/asr/whisper_lib.py
speechtoolkit/classification/__init__.py
speechtoolkit/classification/languageclassification.py
speechtoolkit/data/__init__.py
speechtoolkit/data/languages.py
speechtoolkit/tts/__init__.py
speechtoolkit/tts/styletts2_lib.py
speechtoolkit/utils/__init__.py
speechtoolkit/utils/device.py
speechtoolkit/vc/__init__.py
speechtoolkit/vc/lvc_lib.py
speechtoolkit/vc/ns3vc_lib.py
speechtoolkit-0.0.5.dist-info/METADATA
speechtoolkit-0.0.5.dist-info/WHEEL
speechtoolkit-0.0.5.dist-info/top_level.txt
speechtoolkit-0.0.5.dist-info/RECORD
