Metadata-Version: 2.1
Name: speechtoolkit
Version: 0.0.5
Summary: ML for Speech presents SpeechToolkit, a unified, all-in-one toolkit for TTS, ASR, VC, & other models.
Home-page: https://github.com/ml-for-speech/speechtoolkit
Author: ml-for-speech
Requires-Dist: soundfile
Requires-Dist: librosa
Requires-Dist: transformers
Requires-Dist: torch
Requires-Dist: optimum
Requires-Dist: txtsplit
Provides-Extra: all
Requires-Dist: lvc ; extra == 'all'
Requires-Dist: ns3vc ; extra == 'all'
Requires-Dist: flash-attn ; extra == 'all'
Requires-Dist: openai-whisper ; extra == 'all'
Requires-Dist: mfs-styletts2 ; extra == 'all'
Provides-Extra: asr
Requires-Dist: openai-whisper ; extra == 'asr'
Provides-Extra: dev
Requires-Dist: mkdocs ; extra == 'dev'
Requires-Dist: mkautodoc ; extra == 'dev'
Provides-Extra: fa2
Requires-Dist: flash-attn ; extra == 'fa2'
Provides-Extra: tts
Requires-Dist: mfs-styletts2 ; extra == 'tts'
Provides-Extra: vc
Requires-Dist: lvc ; extra == 'vc'
Requires-Dist: ns3vc ; extra == 'vc'
